arzen/__init__.py
arzen/foo.py
arzen-0.0.1.dist-info/METADATA
arzen-0.0.1.dist-info/WHEEL
arzen-0.0.1.dist-info/top_level.txt
arzen-0.0.1.dist-info/RECORD
