Metadata-Version: 2.1
Name: arzen
Version: 0.0.1
Summary: Utilities for CLI apps for Arzen
Home-page: UNKNOWN
Author: Arzen Tools
Author-email: code@arzen.sh
License: UNKNOWN
Platform: UNKNOWN
